{ "height":20,
 "layers":[
        {
         "data":[12, 12, 7, 7, 7, 7, 7, 7, 7, 7, 7, 7, 7, 7, 7, 7, 7, 7, 7, 7, 7, 7, 7, 12, 12, 12, 12, 7, 2, 2, 2, 2, 2, 2, 2, 2, 2, 2, 2, 2, 2, 2, 2, 2, 2, 2, 2, 7, 12, 12, 12, 12, 7, 2, 2, 2, 2, 2, 2, 2, 2, 2, 2, 2, 2, 2, 2, 2, 2, 2, 2, 2, 7, 12, 12, 12, 12, 7, 2, 2, 2, 2, 2, 2, 2, 2, 2, 2, 2, 2, 2, 2, 2, 2, 2, 2, 2, 7, 12, 12, 12, 12, 12, 1, 1, 1, 2, 2, 2, 2, 2, 2, 2, 2, 2, 2, 2, 2, 2, 1, 1, 1, 12, 12, 12, 12, 12, 7, 2, 2, 2, 2, 2, 2, 2, 2, 2, 2, 2, 2, 2, 2, 2, 2, 2, 2, 2, 7, 12, 12, 12, 12, 7, 2, 2, 2, 2, 2, 2, 2, 2, 2, 2, 2, 2, 2, 2, 2, 2, 2, 2, 2, 7, 12, 12, 12, 12, 7, 2, 2, 2, 2, 2, 2, 2, 2, 2, 2, 2, 2, 2, 2, 2, 2, 2, 2, 2, 7, 12, 12, 12, 12, 7, 2, 2, 2, 2, 2, 2, 2, 1, 1, 1, 1, 1, 1, 1, 1, 1, 2, 2, 2, 7, 12, 12, 12, 12, 12, 1, 1, 1, 2, 2, 2, 2, 1, 1, 1, 1, 1, 1, 1, 1, 1, 1, 1, 1, 12, 12, 12, 12, 12, 12, 1, 1, 1, 2, 2, 2, 2, 1, 1, 1, 1, 1, 1, 1, 1, 1, 2, 2, 1, 12, 12, 12, 12, 12, 12, 1, 1, 1, 2, 2, 2, 2, 1, 1, 1, 1, 1, 1, 1, 1, 1, 1, 1, 1, 12, 12, 12, 12, 12, 7, 2, 2, 2, 2, 2, 2, 2, 1, 1, 1, 1, 1, 1, 1, 1, 1, 2, 2, 2, 7, 12, 12, 12, 12, 7, 2, 2, 2, 2, 2, 2, 2, 2, 2, 2, 2, 2, 2, 2, 2, 2, 2, 2, 2, 7, 12, 12, 12, 12, 7, 2, 2, 2, 2, 2, 2, 2, 2, 2, 2, 2, 2, 2, 2, 2, 2, 2, 2, 2, 7, 12, 12, 12, 12, 12, 1, 1, 1, 2, 2, 2, 2, 2, 2, 2, 2, 2, 2, 2, 2, 2, 1, 1, 1, 12, 12, 12, 12, 12, 7, 2, 2, 2, 2, 2, 2, 2, 2, 2, 2, 2, 2, 2, 2, 2, 2, 2, 2, 2, 7, 12, 12, 12, 12, 7, 2, 2, 2, 2, 2, 2, 2, 2, 2, 2, 2, 2, 2, 2, 2, 2, 2, 2, 2, 7, 12, 12, 12, 12, 7, 2, 2, 2, 2, 2, 2, 2, 2, 2, 2, 2, 2, 2, 2, 2, 2, 2, 2, 2, 7, 12, 12, 12, 12, 7, 7, 7, 7, 7, 7, 7, 7, 7, 7, 7, 7, 7, 7, 7, 7, 7, 7, 7, 7, 7, 12, 12],
         "height":20,
         "name":"Tile Layer 1",
         "opacity":1,
         "type":"tilelayer",
         "visible":true,
         "width":25,
         "x":0,
         "y":0
        }, 
        {
         "height":20,
         "name":"Object Layer 1",
         "objects":[
                {
                 "height":51,
                 "name":"switch a",
                 "properties":
                    {
                     "group":"a"
                    },
                 "type":"switch",
                 "visible":true,
                 "width":54,
                 "x":372,
                 "y":-10
                }, 
                {
                 "height":40,
                 "name":"light a",
                 "properties":
                    {
                     "group":"a",
                     "is_on":"false"
                    },
                 "type":"light",
                 "visible":true,
                 "width":44,
                 "x":251,
                 "y":156
                }, 
                {
                 "height":40,
                 "name":"angel",
                 "properties":
                    {
 
                    },
                 "type":"angel",
                 "visible":true,
                 "width":43,
                 "x":379,
                 "y":122
                }, 
                {
                 "height":36,
                 "name":"dark player",
                 "properties":
                    {
 
                    },
                 "type":"dark_player",
                 "visible":true,
                 "width":37,
                 "x":478,
                 "y":63
                }, 
                {
                 "height":36,
                 "name":"light player",
                 "properties":
                    {
 
                    },
                 "type":"light_player",
                 "visible":true,
                 "width":37,
                 "x":442,
                 "y":64
                }, 
                {
                 "height":40,
                 "name":"angel",
                 "properties":
                    {
 
                    },
                 "type":"angel",
                 "visible":true,
                 "width":43,
                 "x":379,
                 "y":510
                }, 
                {
                 "height":38,
                 "name":"light",
                 "properties":
                    {
                     "is_on":"true"
                    },
                 "type":"light",
                 "visible":true,
                 "width":39,
                 "x":508,
                 "y":317
                }, 
                {
                 "height":38,
                 "name":"light",
                 "properties":
                    {
                     "is_on":"true"
                    },
                 "type":"light",
                 "visible":true,
                 "width":39,
                 "x":380,
                 "y":318
                }, 
                {
                 "height":40,
                 "name":"light a",
                 "properties":
                    {
                     "group":"a",
                     "is_on":"false"
                    },
                 "type":"light",
                 "visible":true,
                 "width":44,
                 "x":379,
                 "y":157
                }, 
                {
                 "height":40,
                 "name":"light a",
                 "properties":
                    {
                     "group":"a",
                     "is_on":"false"
                    },
                 "type":"light",
                 "visible":true,
                 "width":44,
                 "x":508,
                 "y":158
                }, 
                {
                 "height":40,
                 "name":"light a",
                 "properties":
                    {
                     "group":"a",
                     "is_on":"false"
                    },
                 "type":"light",
                 "visible":true,
                 "width":44,
                 "x":506,
                 "y":475
                }, 
                {
                 "height":40,
                 "name":"light a",
                 "properties":
                    {
                     "group":"a",
                     "is_on":"false"
                    },
                 "type":"light",
                 "visible":true,
                 "width":44,
                 "x":378,
                 "y":476
                }, 
                {
                 "height":40,
                 "name":"light a",
                 "properties":
                    {
                     "group":"a",
                     "is_on":"false"
                    },
                 "type":"light",
                 "visible":true,
                 "width":44,
                 "x":250,
                 "y":476
                }, 
                {
                 "height":40,
                 "name":"devil",
                 "properties":
                    {
 
                    },
                 "type":"devil",
                 "visible":true,
                 "width":43,
                 "x":121,
                 "y":123
                }, 
                {
                 "height":40,
                 "name":"devil",
                 "properties":
                    {
 
                    },
                 "type":"devil",
                 "visible":true,
                 "width":43,
                 "x":634,
                 "y":476
                }, 
                {
                 "height":36,
                 "name":"box",
                 "properties":
                    {
 
                    },
                 "type":"box",
                 "visible":true,
                 "width":40,
                 "x":634,
                 "y":317
                }, 
                {
                 "height":36,
                 "name":"box",
                 "properties":
                    {
 
                    },
                 "type":"box",
                 "visible":true,
                 "width":40,
                 "x":444,
                 "y":319
                }, 
                {
                 "height":41,
                 "name":"window light",
                 "properties":
                    {
                     "is_on":"true",
                     "range":"4.5"
                    },
                 "type":"window_light",
                 "visible":true,
                 "width":39,
                 "x":737,
                 "y":125
                }, 
                {
                 "height":41,
                 "name":"window light",
                 "properties":
                    {
                     "is_on":"true",
                     "range":"4.5"
                    },
                 "type":"window_light",
                 "visible":true,
                 "width":39,
                 "x":28,
                 "y":476
                }, 
                {
                 "height":41,
                 "name":"window light",
                 "properties":
                    {
                     "is_on":"true",
                     "range":"4.5"
                    },
                 "type":"window_light",
                 "visible":true,
                 "width":39,
                 "x":733,
                 "y":476
                }, 
                {
                 "height":41,
                 "name":"window light",
                 "properties":
                    {
                     "is_on":"true",
                     "range":"4.5"
                    },
                 "type":"window_light",
                 "visible":true,
                 "width":39,
                 "x":29,
                 "y":124
                }, 
                {
                 "height":41,
                 "name":"window light",
                 "properties":
                    {
                     "is_on":"true",
                     "range":"4.5"
                    },
                 "type":"window_light",
                 "visible":true,
                 "width":39,
                 "x":29,
                 "y":347
                }, 
                {
                 "height":41,
                 "name":"window light",
                 "properties":
                    {
                     "is_on":"true",
                     "range":"4.5"
                    },
                 "type":"window_light",
                 "visible":true,
                 "width":39,
                 "x":27,
                 "y":315
                }, 
                {
                 "height":41,
                 "name":"window light",
                 "properties":
                    {
                     "is_on":"true",
                     "range":"4.5"
                    },
                 "type":"window_light",
                 "visible":true,
                 "width":39,
                 "x":733,
                 "y":285
                }, 
                {
                 "height":41,
                 "name":"window light",
                 "properties":
                    {
                     "is_on":"true",
                     "range":"4.5"
                    },
                 "type":"window_light",
                 "visible":true,
                 "width":39,
                 "x":27,
                 "y":283
                }, 
                {
                 "height":41,
                 "name":"window light",
                 "properties":
                    {
                     "is_on":"true",
                     "range":"4.5"
                    },
                 "type":"window_light",
                 "visible":true,
                 "width":39,
                 "x":735,
                 "y":347
                }, 
                {
                 "height":41,
                 "name":"window light",
                 "properties":
                    {
                     "is_on":"true",
                     "range":"4.5"
                    },
                 "type":"window_light",
                 "visible":true,
                 "width":39,
                 "x":733,
                 "y":318
                }],
         "opacity":1,
         "type":"objectgroup",
         "visible":true,
         "width":25,
         "x":0,
         "y":0
        }],
 "orientation":"orthogonal",
 "properties":
    {
 
    },
 "tileheight":32,
 "tilesets":[
        {
         "firstgid":1,
         "image":"grid.png",
         "imageheight":128,
         "imagewidth":192,
         "margin":0,
         "name":"grid",
         "properties":
            {
 
            },
         "spacing":0,
         "tileheight":32,
         "tileproperties":
            {
             "0":
                {
                 "type":"floor"
                },
             "1":
                {
                 "type":"floor"
                },
             "14":
                {
                 "type":"window"
                },
             "15":
                {
                 "type":"mirror"
                },
             "2":
                {
                 "type":"dim_lamp"
                },
             "21":
                {
                 "type":"mirror"
                },
             "3":
                {
                 "type":"switch"
                },
             "4":
                {
                 "type":"devil"
                },
             "5":
                {
                 "type":"angel"
                },
             "6":
                {
                 "type":"wall"
                },
             "8":
                {
                 "type":"lit_lamp"
                },
             "9":
                {
                 "type":"box"
                }
            },
         "tilewidth":32
        }, 
        {
         "firstgid":25,
         "image":"..\/..\/tileset.jpg",
         "imageheight":256,
         "imagewidth":256,
         "margin":0,
         "name":"more tiles",
         "properties":
            {
 
            },
         "spacing":0,
         "tileheight":32,
         "tilewidth":32
        }],
 "tilewidth":32,
 "version":1,
 "width":25
}
